__init__.py
main.py
maker.py
repo.py
runcmd.py
template.py
okuldaogrenilen-0.1.3.dist-info/LICENSE
okuldaogrenilen-0.1.3.dist-info/METADATA
okuldaogrenilen-0.1.3.dist-info/WHEEL
okuldaogrenilen-0.1.3.dist-info/entry_points.txt
okuldaogrenilen-0.1.3.dist-info/top_level.txt
okuldaogrenilen-0.1.3.dist-info/RECORD
