Metadata-Version: 2.1
Name: okuldaogrenilen
Version: 0.1.3
Summary: OkuldaOgrenilen github hesabı için cli aracı
Author-email: ahmetcanisik <imcanisik@gmail.com>
Project-URL: Homepage, https://github.com/OkuldaOgrenilen/oo
Project-URL: Issues, https://github.com/pypa/OkuldaOgrenilen/oo/issues
Classifier: Programming Language :: Python :: 3
Classifier: License :: OSI Approved :: MIT License
Classifier: Operating System :: OS Independent
Requires-Python: >=3.8
License-File: LICENSE
Requires-Dist: rich >=13.8.1
Requires-Dist: typer >=0.12.5
Requires-Dist: requests >=2.32.3
